triplespec_focus/__init__.py
triplespec_focus/entrypoints.py
triplespec_focus/triplespec_focus.py
triplespec_focus/utils.py
triplespec_focus/tests/__init__.py
triplespec_focus/tests/test_triplespec_focus.py
triplespec_focus/tests/test_utils.py
triplespec_focus-1.0.2.dist-info/LICENSE
triplespec_focus-1.0.2.dist-info/METADATA
triplespec_focus-1.0.2.dist-info/WHEEL
triplespec_focus-1.0.2.dist-info/entry_points.txt
triplespec_focus-1.0.2.dist-info/top_level.txt
triplespec_focus-1.0.2.dist-info/RECORD
