Metadata-Version: 2.1
Name: triplespec-focus
Version: 1.0.2
Summary: Finds best focus for TripleSpec spectrograph based on a series of images obtained with different focus values
Home-page: https://github.com/soar-telescope/triplespec_focus
Author: Simon Torres
Author-email: simon.torres@noirlab.edu
License: BSD-3-Clause
Requires-Python: >=3.6
License-File: LICENSE
Requires-Dist: astropy
Requires-Dist: matplotlib
Requires-Dist: numpy
Requires-Dist: pandas
Requires-Dist: photutils
Requires-Dist: scipy
Requires-Dist: ccdproc
Provides-Extra: docs
Requires-Dist: matplotlib ; extra == 'docs'
Requires-Dist: sphinx ; extra == 'docs'
Requires-Dist: sphinx-rtd-theme ; extra == 'docs'
Provides-Extra: test
Requires-Dist: pytest-cov ; extra == 'test'
Requires-Dist: coverage ; extra == 'test'
Requires-Dist: requests ; extra == 'test'
